Predictor/__init__.py
Predictor/predictor.py
PredictorNachiket-0.2.dist-info/METADATA
PredictorNachiket-0.2.dist-info/WHEEL
PredictorNachiket-0.2.dist-info/top_level.txt
PredictorNachiket-0.2.dist-info/RECORD
